target_postgres/__init__.py
target_postgres/denest.py
target_postgres/exceptions.py
target_postgres/json_schema.py
target_postgres/postgres.py
target_postgres/singer.py
target_postgres/singer_stream.py
target_postgres/sql_base.py
target_postgres/stream_tracker.py
target_postgres/target_tools.py
singer_target_postgres-0.2.4.dist-info/LICENSE
singer_target_postgres-0.2.4.dist-info/METADATA
singer_target_postgres-0.2.4.dist-info/WHEEL
singer_target_postgres-0.2.4.dist-info/entry_points.txt
singer_target_postgres-0.2.4.dist-info/top_level.txt
singer_target_postgres-0.2.4.dist-info/RECORD
