Metadata-Version: 2.1
Name: singer-target-postgres
Version: 0.2.4
Summary: Singer.io target for loading data into postgres
Home-page: https://github.com/datamill-co/target-postgres
Author: datamill
License: UNKNOWN
Platform: UNKNOWN
Classifier: Programming Language :: Python :: 3 :: Only
Requires-Dist: arrow (==0.15.5)
Requires-Dist: psycopg2 (==2.8.5)
Requires-Dist: psycopg2-binary (==2.8.5)
Requires-Dist: singer-python (==5.9.0)
Provides-Extra: tests
Requires-Dist: chance (==0.110) ; extra == 'tests'
Requires-Dist: Faker (==4.0.3) ; extra == 'tests'
Requires-Dist: pytest (==5.4.1) ; extra == 'tests'
